{"id":"2ilku70909st8lyzpa2n3og","title":"NIEMOpen","desc":"community-driven, common vocabulary that enables efficient information exchange across diverse public and private organizations","updated":1721788672523,"created":1721788559078,"custom":{},"fname":"prdct.niem-open","type":"note","vault":{"fsPath":"public-notes","remote":{"type":"git","url":"git@github.com:djradon/public-notes.git"},"name":"public-notes"},"contentHash":"961bb3896ebe2810c11f160db30d8e48","links":[{"type":"wiki","from":{"fname":"prdct.niem-open","id":"2ilku70909st8lyzpa2n3og","vaultName":"public-notes"},"value":"c.ontology","position":{"start":{"line":3,"column":3,"offset":28},"end":{"line":3,"column":17,"offset":42},"indent":[]},"xvault":false,"sameFile":false,"to":{"fname":"c.ontology"}}],"anchors":{},"children":[],"parent":"6q10hkz3zuvnueqa9slqqmu","data":{}}
