{"id":"5v37tf9s31jovfewiiu25q6","title":"Trld","desc":"transpilable implementation of algorithms for working with Linked Data as JSON-LD. This includes translating to and from various RDF syntaxes and mapping of vocabularies.","updated":1720329455501,"created":1720329414461,"custom":{},"fname":"prdct.trld","type":"note","vault":{"fsPath":"public-notes","remote":{"type":"git","url":"git@github.com:djradon/public-notes.git"},"name":"public-notes"},"contentHash":"c602c3e1bc8bb3eb9ac7f6f72b397c4a","links":[{"from":{"fname":"prdct.linked-data-target-value-maps","id":"yqcey40ky3aqprq2rq4uogo","vaultName":"public-notes"},"type":"backlink","position":{"start":{"line":3,"column":12,"offset":47},"end":{"line":3,"column":26,"offset":61},"indent":[]},"value":"prdct.trld"}],"anchors":{},"children":[],"parent":"6q10hkz3zuvnueqa9slqqmu","data":{}}
