{"id":"60phhngq6c6wab0m5y1qlng","title":"Try .NET","desc":"","updated":1689961617712,"created":1689961600390,"custom":{},"fname":"prdct.try-net","type":"note","vault":{"fsPath":"public-notes","remote":{"type":"git","url":"git@github.com:djradon/public-notes.git"},"name":"public-notes"},"contentHash":"0a55ff341e7af6bf5c7a371d132205c8","links":[],"anchors":{"resources":{"type":"header","text":"Resources","value":"resources","line":9,"column":0,"depth":2}},"children":[],"parent":"6q10hkz3zuvnueqa9slqqmu","data":{}}
