{"id":"660teaxyge8yvn80cexpuew","title":"Ngraph","desc":"","updated":1701160062902,"created":1701158938246,"repo":"https://github.com/anvaka/ngraph.graph","features":["You can also associate arbitrary object with a link using third optional argument of addLink() method","Whenever someone changes your graph you can listen to notifications","multigraph support - but https://github.com/anvaka/ngraph.graph/issues/19"],"cons":["no query language"],"custom":{"repo":"https://github.com/anvaka/ngraph.graph","features":["You can also associate arbitrary object with a link using third optional argument of addLink() method","Whenever someone changes your graph you can listen to notifications","multigraph support - but https://github.com/anvaka/ngraph.graph/issues/19"],"cons":["no query language"]},"fname":"prdct.ngraph","type":"note","vault":{"fsPath":"public-notes","remote":{"type":"git","url":"git@github.com:djradon/public-notes.git"},"name":"public-notes"},"contentHash":"311b62a2f37b737a0b49234e119e5ed6","links":[],"anchors":{},"children":[],"parent":"6q10hkz3zuvnueqa9slqqmu","data":{}}
