{"id":"7272514wvvn78ppl0gxbz1o","title":"Addressable Resources","desc":"","updated":1725472989445,"created":1724867449827,"custom":{},"fname":"ar","type":"note","vault":{"fsPath":"public-notes","remote":{"type":"git","url":"git@github.com:djradon/public-notes.git"},"name":"public-notes"},"contentHash":"6680228ce97107a77f03448db2237881","links":[{"from":{"fname":"root","id":"CpS9sdQeO83XthdjEzqoL","vaultName":"public-notes"},"type":"backlink","position":{"start":{"line":13,"column":5,"offset":453},"end":{"line":13,"column":11,"offset":459},"indent":[]},"value":"ar"}],"anchors":{},"children":["snrad0bldvms5ifxwbazlnz","gf0oi0n4b69pugmb7i3vhn2","1uvqmgbpmiku442mpejx26k","r387ij47xqp5161gs34f7q2","9t4gwbk0fqhawfob2u74pxl","gss72xpmblpsxet5vu7ak9m","yc83iqzyps97q2w3c5r103j","izddhcpi5q7a9z45km4tvgs","f7663ygbq8lf0sv3t18chbc","geowoyp3iip20n7kjq1royq","jxej1bzfm42cbouwzcl0cd4","5vlhoqsdi9n9a6nb8wun0t8","memhjov0iuoyftelv41me2v","l3kei9ohjtb2qg0mmaemwyw","chxm3u1se1co6wplcw15hb9","VL8fbMaMBaa34Asf3cFB5","xcyhbcazc7srl5osd5mkeoq","g2gyfldfo1r05zlpvulxzss","r23kfh00vk1jrcih1np35f4","i9r29hqt32hqvq7lhol10s2","mmPDPwOkZdEO0cZ3uxiyX","ln4t7udwelrwqatvk01f4js","878kg6rkvxkaldjauswgqk5","51aty4mlflj5k7lj0eogjlj","byvjpewkoi0a5jw7300hb1h","labemoqi65dnwe8jhklw51e","73kcj3ohj07u985kspptsjx","pqhijdt37x8srm6hq47dmsi","sogw5ltzq6qgctlvh2xw4yp","u1yx76nfnn6pa7zejvnjd4p","a3dr7h9nhc1qj39e06umuyb","cBHJPUs59nEVLwpNoyTzL","nctdsff05919pfyyz2t60yt","inambqlxiimpcrwvuc5y8sk","30cbzccaqpopf0hlfznqc5h","8q3wkicfurf0iva76qwio2k","cswid8jbys6wa80jab1m5uj","z3y28yj3kezh1057ok51msp","auyehduolukovzbngjx32ff","4rq7bnrndqqm3mn5u7row58","l8mxuujoo2p7ydvttea8v4n","fg24otxt64z8qpoopak4v9x","yng2s0uzrwqqazgctop62ij","tam3ywm8bvxetws1gzrot3g","fanwgsa7f4twi97b5h2hbz9","qjlho8yxi7n6pe1uebf81b5","pf8h1vgm5j307dsjbmuzz00","xb6nobl4lbc2sllopvsvwou","9kufekcvm9hfbgeeqdjotuz","2f7wd57y4s4nf82qbfecem3","kf04rf4jt9dzqyjsx1n9wuz","tbnxcw3dk7gun5jxt899le3","azm5f66z3d0frqozkd2ww55","g1j59g4r71qlggbkq9iwsk5","edddvfsdrnu95mw4gy9fhcl","vdeukuusda1ynjl6m8l41pd","x07avwnfhpa21xstgmome8u","zl65cy7tzy6rx5o6c76v3v6","hkxah194dpizzj8cjud679r","fa1vqnpp2eze4kmn3htnto2","dbmkzftjfuitdz74wrqfhz4","lknkpg2nl55x37sttbzipsn","03g5n90pq0fbkoqz7yi9l2e","0fiagbzdfbnggm3dqf0vtgg","ebbryqwe4teb7244b40p3eo","phzcmmp1orhkve8ohh3kg2o","c42mztophejelcfldriet8b","8p5z4opvu9ou6qjcliuif9d","t6ebsghgw5xwdiku27e1kx7","p2qt14w5ofpgh6g9uzl14ef","fw55hkk22tn2gc4uz6rgk04","0xqvayx6pfhxxd8dzl2g00l","xx8san1pymdwbciw9xijvh0","8sxm32xsm2tdkfwu4edqju3","g71l6r1dks3pqp45v2z4863","03prptw7a8zmx9clcm7nv5g","xmqsmknpk0g91ivipkl72pe","smsmtikxc0h3x1urabxafrf","iynlp25h6qqigrbt50f0yqr","h1e3ywyxb0bgsnj96y1krs0","zbgt8ydiqczaxg4mn5kutyg","67wg95w9f1jzj9nd365uf4a","vr6c4kff48dfltfmrmjmh7y","h8tsd15fz1s94who7bwq5i7","38e3xe7s0etrypk9h69rzkf","w7de1fxru355f7e3cuchwdh","74jdz5jflj41c66lsn2acm2","iiqm9djy74ll11ttbw4g5ow","lkrtyir3nc1ujpqk3rf5uep","awheu7lrgw0ub11booquqpi","xa1sqwopiyjysp3ukgbt3zm","6v41muv04cpr9y6o3rinj38","45iiar5pg6hcwztxbpitk2j","a5xei04z604tjqkzl747iyf","nc59i85igunik8suby2gkml","il3lto3ao7xvpuzztgv4sdm","2zdp6fm5giqfpbqmd2l3lkk","UDyKdrUPJBObO6lxqigxN","pkfa0zjx6a69hnmhxd9qos6","w53bteevk4vb3vjy2bvux8z","p2akfpv5p9bvc0aq1vu3m3a","c02i62y8vw0n0m4qzdcuri2","k6btcrgsyz8jgwmesl67lyh","og8bk3c5ikxqyny89c3q0m4","u9zazfs4layth17qnl0gmn3","nqymj2nweaa7b35u7gpzo6m","1opk5w6icu8ighdf1sao1t9","4yfhv81tilbhw4j33u5h635","tz5z4fjjwj1i8zh2ypy87dm","fcvv57du1m0ub248tl5w65v","h00qd3mljukg0lhqh3fi2lf","ghlsg7kgdqzmhsebsf4df3m","pj7hxg43l92nle5z806eax9","dzalivqcjbn3xbqqu1gtjfu","qvg03gclyk3cl38prlc08gu","wxfdcwhehl9ok13rd8d80et","0sa4yhxdkb3nfow48rrgu80","b8fqqegeprbro823sohrgix","0dh42jiibot21g3gvp8k0hk","gzfq49b8koqu871wrot4v2g","73a7e2zni7a0pw59ix4n4fz","grnxd8eu85x0cx2akmwmnbu","WS3dT7KhUGGGRnXRqYV5l","vh3kwupydfe5k2zkjf59mt5","qu420farh0quvfflsq15umi","yx47xgbt58vbnxjm6pf7rt9","u49m20ho9i14vyy6ns5xif8","1hob5aisv4xlgfcdev0gwr2","9egcmt03twujy3p9d7ntrmy","f6xxx08laju45jj4zcyopwo","nizjazfohi0wjm1yqkxitj4","irpbecuanb3c1sa3fa2q23m","w57vzmkc95sfevsptwd2y3s","q9aopy11berm8bok7gyt8rr","bq5pnupkcc2vnfv7scf812k","s5w0ggdd5atbfsbd78i4q69","t0d5v30oidhbkotntd98p58","sfgewroeyzaqx3g3xdodnmm","ez8zsw337pzfhwkzxzh6sss","m7ujff798n9ggskputesgm4","ln9msn4gjrhb2y18855kgi9","tkyah1ebrik9myz67t90juk","bp4xf4smzbtvrq14zbt1vwf","brc52nyn17mpphc3y55s3cd","ykqsqfdmjvrspvms732ztxo","wpwzq9ttwck0zgdxivomgiq","tzftbab7cr7tvs7er5xfjau","sfqfvpfatw54z0fc58j9rew","oddj7hjyfuz8qbqs6eu7wmu","qhe6rkj432owo5j4yf4qxby","q681nezkfg2j4ud8au3il3w","DF1TFWyAJMF9GOt3ZmEF5","x7am99vb2ugu7r77ry3hldl","uejnqikaw22lpusyoksex5v","t1y8ied34zs4wpx92ynv5jv","8rajl5vlvylqjny5hgr1t5l","aSdM23LoVqx4eXymCMGvy","v7jys6kztnbivkfl9y3g7fr","u37iaufehfennb7gj7wdziw","cyqm8yjqdj9sg0euzm2c210","6ng58rce8bz87shvkwzodos","78aevxyxwdp3m1itb6ljkud","kamd4acwk3ix5og31ush1po","gqrsnhrlvp3jp8pwdwi4hl5","j5iltrasjf6fspig38d2efk","crm96ivxggown3jd99hd48n","y5nd0h4hjkepb403xop60yq","72k96bp277imkafg599jyly","07cx1ov2u8m5hxkatx2g512","psmltou2po857f068x03d7x","ibynfb2m7ohzzufji9m063s","0xpjwx8x6b3ckaecawoky2t","s7n78pt3m183qt0coee5ilj","pecaiit3ve4024c32wkjfsy","tvuaus59u0nykq6qls20rv1","4kw39mf0ye3zaxv050376sa","uvqciflmx9bw4ki332ij26r","84vgps41y6iae8z03sgrnir","5x4czy7ll20i5eg8kuynyft","3pwkeuh0e1c0zdkmxkqwema","wiw9qpfatgigmxehpghorb4","x219kze2gk6lbvyfa7ftlv5","7zcuhutgloqw4107hi7hl8v","ssnwov20zmlpd9f1ik1cr02","w37gq6wi1cbz3zyfc20de16","d9v5u117rb2nf3btzr3wz3k","4y17ummbtrsmrs4o6d8xfxm","ub4u5ch2j5g63t9coa9x7k4","mltrsxxtyk69l9t3cc5kw6w","8ggc7back9k2qbpp06iyi06","d74fo4w39vwnjg4rkncv2se","lwivxblggizkm5mmf0u9t3w","z4eyx1bblv40g0r8hn64ap3","8y7ioma66mfn6h3gqj7uw1t","ksnp6g8sw5hhdhdigjsbsgy","cj1rga91zbmfhb430dkai94","j1dkhkkdicpzq7pfrco1jb4","zqh4p0cz044lzzvgfmmpogn","t5hp66p9u545s2wfgd7kcfp","dmGGO7inr6vmMgVGrORi8","g1ve2g80tly07mel94q1z3v","b5hu8kfmzaudd5wenbx369u","0tvpqxmq2kcs3a96fg8o2qq","hcezf68tojejcin18j2pex5","azhbah4ygqgqcyk5mfxto2i","b3e25l03gj2k8k6n04nygsv","pdrtlyp5mznsnsgbemgcgxm","7l727346n6d3eclic9b9wkb","dtgnl219vxsaye1kczgl3oa","8vn9kyd0k3i6wra9gn2ctfq","31n6gtegjp893vfuiz340ml","ti4xbs4un4n199v91bdr4lk","3soxx69xxsbswz4gkhc4esq","b2cfxfrvhoqezasf2xm2gel","bcd7bjf5lihabcz0rynqcw0","m3s2x1ajzacl8o0sfts1fcd","3shosjiu5pdogqrx1zf182k","b5r5h1ckc8ip13synq0lpjw","cxn4hz7x8dl3uf15sw8z31a","cpdig004z8mcgfc3whw1sdy","g4mcfss08k8e4n3d04hgh3w","knr70d98u0tqx338yeii27u","fn2qciqpu028i9qujf46xxm","818vvx0i0pjd2zy2he2ddel","mcv263t13bem9qlqudieoj8","457i8fje6x9msz7alhfeubq","n15fmuqcl3am3g3f1qpn3k9","ivymuj4reyziig8rz7gp193","vhd7sh6xyrjo36wq5qjybhq","qz09ylhb7g59g1w7q5bksvv","nmgqmbzh6ftaa7jj2woieqa","dmpd20tbhlczkckeuu4lvsi","p784e5cnghmf0bfrbmlmgj1","qfnxzmbgy18kgwbxxi5eswk","swhhgs1d5yef56pvwa7gxsc","vm4l9rwu16c839mou641qu7","q0z5zjqltaykvr7ttt9jtog","ia1ofntismk814syc4sem7r","u49exbzugptwgp5s9dz13wt","grjqhortbt7u0x7zbk09owg","872wdorkpc02okhekgi3uaw","80yvtgiuhc5qusdgpwj4shp","9gofulog8j9a13eqkvs6al8","hbn7zufm2z9eyswr3tlqpp2","s54omiqx3n6lrer92paec95","5g7kzbv9x14tgrl9g6gp7o3","qv2k0ar4j0ef1meop2bzigz","2mt4k5fhye3sazzi9vgqj17","k9md1z2hae9vmhvqz1l6ys6","8c5op36972qc5tmfde0prr9","w13frof5k7hokko2mbixau8","i46abfw2dy6cj0l8w217f8m","h49meunbijyfab83q4d2zdd","052w8g69g0mn7yt290bw7yt","womrky7va0hgj90vrbi544f","j98b2prfue8txvknlxrbkgx","zex0u9fj4saxth28xa6xyj9","iknmpcwul1swnnew1p5k2s0","tla50szfndrzw1fycstyuwh","upnitfop8golat4g2w0v9d9","sc1keesl1p8v8gbsxvpv3fv","yygtrt1i6ryqvorqnq9hypz","xyfb72cup56rnh94g7q8c76","9uw9k0p43dvgxy8sg4iki00","ie5e3vc2syqy51i1elsczeq","plzqijn9u7758ktbdfajvh5","i29qtgl2efb1mh6admnbrpn","5zmo9y5u6z3lk40p8amsqal","h047jpbgu02ugobquqaquzs","9rsjyucb4vovyitek0irgax","ed0y3fbmiiihb437itsn2di","zzoajb1hp4gezmidmjgeyll","umt19japmssk0t1nf9k0xkw","bt9hz3dkw8nj3dz5i2bj608","ogo6wah73a4kkx5nrpaoxo3","i2ye4szm2kdtd98edx1gzvk","6bats7d7d5rpmyivppcxy6f","xv0quojswmla8fgo2flgdrn","tftpwuvya5sgnm6wmxfnkxo","aiw2ts9ndd8nlp9zja2waj8","yqherpc7s58ja1143nuz6g6","4m4l9nvlmyejird5cotf4fq","56xihrxel0g5webdkncrw8a","u6vy2tijt6dd4nw2mclg14b","a42wc66z30xxlppln5hfm3p","bdw88a2hg33br7gvnfn7b0u","cnkaqv6i8oqc3xhqv185wey","jnuuphcvm6auotbtdbnycwh","re5tuhbnd1rg637at2tt72t","ewqur3wpm35tzzw08d06aim","o99h4umwihpwctxh1uwle9u","y9r2mc1bwsmex1zrs86no1q","8xxzk69nn8ynebdzl2awetw","6s7p3q6gyqup47u3p6yjihz","g7go2becrqo6t6xb47zlotq","vxmsqidbj0tj16b775p0moe","9aex3qhygoyjukr22vqhxqn","xxve7p3ht0b9ibe5oi9j83f","8uebjda3bzz5pmg6c23cerv","3jcfwzyit3vhlebd96pwhxh","3po4xhmzlbyhefv4fpan3c0","rot6zt2u2lzikvzztepps42","hoyw6vo8ext34obj8xnywfx","zrc98rsabpni2rp9hsr2kmy","rfai5gj9y25cj2q6t3ma0nt","9ew6fba9of82fxxz6sull5l","lcamxtid0rxnegpakxcjc7i","NVxW9YvTOsnDoISwDVqEJ","rVOjxDvd4AGE2liIhhjVS","29svhyIOLliTANTbzdiJ2","wQIL92LEJ1yCcqwW4fLHU"],"parent":"CpS9sdQeO83XthdjEzqoL","data":{}}
