{"id":"8kByNuGQvK1LWXKO6I113","title":"Grammar","desc":"","updated":1638112809271,"created":1636467638032,"custom":{},"fname":"t.ling.grammar","type":"note","vault":{"fsPath":"public-notes","remote":{"type":"git","url":"git@github.com:djradon/public-notes.git"},"name":"public-notes"},"contentHash":"f5641a7406a6163d76a06b1153516596","links":[],"anchors":{},"children":["WrLiMaxriUSh0NLhu8gX2","zm0nkaheezgj7l4hw9waknb","y09atoi366d79bfc8xmm6zx","iUgN6d2W0i7Dm2LPXj8Qu","gclv4jsvljqwu051sbq883x","bya1yvl5anc25gzbak4slga","EbxwKnt9u3HC4q2sfuDg8","5jkngnz1i19ftk371v08gdc","nh89l3n28q8p3n9h9sotfqt","gTE3JtDyHzjhjDwPxmvZ6","c47nnrkapzkq4p7caxvg7u8","5r0kgbl0uxi5b0z515ng5cq","Fd45mK6CJssb4kEz1FZh3","6jhbf3z3l2crfjlny9zlx4l","5wmc8dgfqxy26r82173lilz","zapmnd4gdnq981j43dmmzrv","knxk5qkzspdoitrueaq1t4g","8pBA2lW8DjAgJisoPu837","efnUiIbGt2JtkfJ8PbDhJ"],"parent":"scEXovx5Fs4yC7bU4wCLb","data":{}}
