{"id":"c4NRshNrRK3hEdOOfNnbk","title":"hadHost","desc":"","updated":1636740645368,"created":1636740609795,"custom":{},"fname":"p.hadHost","type":"note","vault":{"fsPath":"predicates","remote":{"type":"git","url":"git@github.com:djradon/predicates.git"},"name":"predicates"},"contentHash":"f1f4c704ce6998a21d9c56ce557369fe","links":[{"type":"wiki","from":{"fname":"p.hadHost","id":"c4NRshNrRK3hEdOOfNnbk","vaultName":"predicates"},"value":"p.isRelated","position":{"start":{"line":5,"column":3,"offset":6},"end":{"line":5,"column":18,"offset":21},"indent":[]},"xvault":false,"sameFile":false,"to":{"fname":"p.isRelated"}},{"type":"wiki","from":{"fname":"p.hadHost","id":"c4NRshNrRK3hEdOOfNnbk","vaultName":"predicates"},"value":"p.hadPanelist","position":{"start":{"line":5,"column":19,"offset":22},"end":{"line":5,"column":57,"offset":60},"indent":[]},"xvault":true,"sameFile":false,"to":{"fname":"p.hadPanelist","vaultName":"predicates"}},{"from":{"fname":"video.tedx.indigenous-in-plain-sight","id":"tzq0ulqmxvj9uam6iuv6149","vaultName":"public-notes"},"type":"backlink","position":{"start":{"line":3,"column":3,"offset":62},"end":{"line":3,"column":16,"offset":75},"indent":[]},"value":"p.hadHost"}],"anchors":{},"children":[],"parent":"pr50duvmwnfu5pf0zohcftk","data":{}}
