{"id":"ci4ieykm7dck0gq38sfmbud","title":"EventCatalog","desc":"Open Source project that helps you document your events, services and domains","updated":1697565412542,"created":1696014886818,"custom":{},"fname":"prdct.event-catalog","type":"note","vault":{"fsPath":"public-notes","remote":{"type":"git","url":"git@github.com:djradon/public-notes.git"},"name":"public-notes"},"contentHash":"ca0047f42ad10c9ebf167898431d6ca1","links":[{"type":"wiki","from":{"fname":"prdct.event-catalog","id":"ci4ieykm7dck0gq38sfmbud","vaultName":"public-notes"},"value":"c.Software.Tools.Diagramming","alias":"Diagramming","position":{"start":{"line":2,"column":3,"offset":3},"end":{"line":2,"column":47,"offset":47},"indent":[]},"xvault":false,"sameFile":false,"to":{"fname":"c.Software.Tools.Diagramming"}},{"type":"wiki","from":{"fname":"prdct.event-catalog","id":"ci4ieykm7dck0gq38sfmbud","vaultName":"public-notes"},"value":"p.integratesWith","position":{"start":{"line":4,"column":3,"offset":87},"end":{"line":4,"column":23,"offset":107},"indent":[]},"xvault":false,"sameFile":false,"to":{"fname":"p.integratesWith"}},{"type":"wiki","from":{"fname":"prdct.event-catalog","id":"ci4ieykm7dck0gq38sfmbud","vaultName":"public-notes"},"value":"prdct.asyncapi","position":{"start":{"line":4,"column":24,"offset":108},"end":{"line":4,"column":42,"offset":126},"indent":[]},"xvault":false,"sameFile":false,"to":{"fname":"prdct.asyncapi"}},{"type":"wiki","from":{"fname":"prdct.event-catalog","id":"ci4ieykm7dck0gq38sfmbud","vaultName":"public-notes"},"value":"p.supports","position":{"start":{"line":5,"column":3,"offset":129},"end":{"line":5,"column":17,"offset":143},"indent":[]},"xvault":false,"sameFile":false,"to":{"fname":"p.supports"}},{"type":"wiki","from":{"fname":"prdct.event-catalog","id":"ci4ieykm7dck0gq38sfmbud","vaultName":"public-notes"},"value":"prdct.react-flow","position":{"start":{"line":6,"column":5,"offset":149},"end":{"line":6,"column":25,"offset":169},"indent":[]},"xvault":false,"sameFile":false,"to":{"fname":"prdct.react-flow"}},{"type":"wiki","from":{"fname":"prdct.event-catalog","id":"ci4ieykm7dck0gq38sfmbud","vaultName":"public-notes"},"value":"prdct.asyncapi","position":{"start":{"line":7,"column":5,"offset":175},"end":{"line":7,"column":23,"offset":193},"indent":[]},"xvault":false,"sameFile":false,"to":{"fname":"prdct.asyncapi"}},{"from":{"fname":"t.cs.sd.architecture.event-driven","id":"ehflhupgftjncjisnmcxyzy","vaultName":"public-notes"},"type":"backlink","position":{"start":{"line":34,"column":19,"offset":3038},"end":{"line":34,"column":42,"offset":3061},"indent":[]},"value":"prdct.event-catalog"}],"anchors":{},"children":[],"parent":"6q10hkz3zuvnueqa9slqqmu","data":{}}
