{"id":"d63bo2zkaf2ufr7zbcy9xsj","title":"Ndjson","desc":"newline delimited json","updated":1718062444869,"created":1718062367586,"custom":{},"fname":"prdct.ndjson","type":"note","vault":{"fsPath":"public-notes","remote":{"type":"git","url":"git@github.com:djradon/public-notes.git"},"name":"public-notes"},"contentHash":"ed93a1f180457f28682e859688b5f3db","links":[{"type":"wiki","from":{"fname":"prdct.ndjson","id":"d63bo2zkaf2ufr7zbcy9xsj","vaultName":"public-notes"},"value":"prdct.rdflib","position":{"start":{"line":7,"column":3,"offset":101},"end":{"line":7,"column":19,"offset":117},"indent":[]},"xvault":false,"sameFile":false,"to":{"fname":"prdct.rdflib"}},{"from":{"fname":"prdct.hextuples","id":"xqyv74byikdfixf87o22lcq","vaultName":"public-notes"},"type":"backlink","position":{"start":{"line":3,"column":13,"offset":52},"end":{"line":3,"column":29,"offset":68},"indent":[]},"value":"prdct.ndjson"},{"from":{"fname":"ar.ontola.full-stack-linked-data","id":"jhopk9p3diourocvkbdeswf","vaultName":"public-notes"},"type":"backlink","position":{"start":{"line":3,"column":12,"offset":60},"end":{"line":3,"column":28,"offset":76},"indent":[]},"value":"prdct.ndjson"}],"anchors":{"solutions":{"type":"header","text":"Solutions","value":"solutions","line":10,"column":0,"depth":2}},"children":[],"parent":"6q10hkz3zuvnueqa9slqqmu","data":{}}
