{"id":"eOI9pRWCoqmCUww10Mg5k","title":"Bill Watterson Kenyon Commencement","desc":"","updated":1667806606131,"created":1644013393911,"custom":{},"fname":"event.1990.bill-watterson-kenyon-commencement","type":"note","vault":{"fsPath":"public-notes","remote":{"type":"git","url":"git@github.com:djradon/public-notes.git"},"name":"public-notes"},"contentHash":"629b59f04b0acfac1d9dbe7f74e4682f","links":[{"type":"wiki","from":{"fname":"event.1990.bill-watterson-kenyon-commencement","id":"eOI9pRWCoqmCUww10Mg5k","vaultName":"public-notes"},"value":"c.resource","position":{"start":{"line":4,"column":3,"offset":5},"end":{"line":4,"column":17,"offset":19},"indent":[]},"xvault":false,"sameFile":false,"to":{"fname":"c.resource"}},{"type":"wiki","from":{"fname":"event.1990.bill-watterson-kenyon-commencement","id":"eOI9pRWCoqmCUww10Mg5k","vaultName":"public-notes"},"value":"ar.the-marginalian.this-is-water-david-foster-wallace-on-life","alias":"https://www.themarginalian.org/2012/09/12/this-is-water-david-foster-wallace/","position":{"start":{"line":5,"column":5,"offset":24},"end":{"line":5,"column":148,"offset":167},"indent":[]},"xvault":false,"sameFile":false,"to":{"fname":"ar.the-marginalian.this-is-water-david-foster-wallace-on-life"}},{"type":"wiki","from":{"fname":"event.1990.bill-watterson-kenyon-commencement","id":"eOI9pRWCoqmCUww10Mg5k","vaultName":"public-notes"},"value":"tags.recommended","alias":"#recommended","position":{"start":{"line":5,"column":149,"offset":168},"end":{"line":5,"column":161,"offset":180},"indent":[]},"xvault":false,"to":{"fname":"tags.recommended"}}],"anchors":{},"children":[],"parent":"dmp8jfgb8gm2424j2tj1fda","data":{}}
