{"id":"fg61p0gsr616ncfokwf5l7s","title":"Everquest","desc":"","updated":1698606717281,"created":1698605911464,"custom":{},"fname":"game.everquest","type":"note","vault":{"fsPath":"public-notes","remote":{"type":"git","url":"git@github.com:djradon/public-notes.git"},"name":"public-notes"},"contentHash":"722c67cd3c16a415176620ae2bc2872a","links":[{"from":{"fname":"t.rec.game.time-locked-progression","id":"16iprc9quob3o9096wybulk","vaultName":"public-notes"},"type":"backlink","position":{"start":{"line":2,"column":11,"offset":11},"end":{"line":2,"column":29,"offset":29},"indent":[]},"value":"game.everquest"}],"anchors":{"references":{"type":"header","text":"References","value":"references","line":8,"column":0,"depth":2}},"children":[],"parent":"48sncuimn75uzjhk3fhpnzk","data":{}}
