{"id":"h0axurclgbeyjcvt6tfje2q","title":"GraphQL Sse","desc":"","updated":1701280247432,"created":1701280242626,"repo":"https://github.com/enisdenjo/graphql-sse","custom":{"repo":"https://github.com/enisdenjo/graphql-sse"},"fname":"prdct.graphql-sse","type":"note","vault":{"fsPath":"public-notes","remote":{"type":"git","url":"git@github.com:djradon/public-notes.git"},"name":"public-notes"},"contentHash":"3ec55878ba277a7f3d9272cbcbe41dcb","links":[{"from":{"fname":"prdct.server-sent-events","id":"5o0t67dslcj0vyo8z6yrpgh","vaultName":"public-notes"},"type":"backlink","position":{"start":{"line":21,"column":15,"offset":1013},"end":{"line":21,"column":36,"offset":1034},"indent":[]},"value":"prdct.graphql-sse"}],"anchors":{},"children":[],"parent":"6q10hkz3zuvnueqa9slqqmu","data":{}}
