{"id":"i9YO8Z7TUEkxLONAPYgu9","title":"isTopicOfDiscussion","desc":"","updated":1671318838954,"created":1637846915029,"custom":{},"fname":"p.isTopicOfDiscussion","type":"note","vault":{"fsPath":"public-notes","remote":{"type":"git","url":"git@github.com:djradon/public-notes.git"},"name":"public-notes"},"contentHash":"e0558b5ab0614cc13c25b28feb4a2315","links":[{"type":"wiki","from":{"fname":"p.isTopicOfDiscussion","id":"i9YO8Z7TUEkxLONAPYgu9","vaultName":"public-notes"},"value":"c.sphere","position":{"start":{"line":4,"column":3,"offset":5},"end":{"line":4,"column":15,"offset":17},"indent":[]},"xvault":false,"sameFile":false,"to":{"fname":"c.sphere"}},{"type":"wiki","from":{"fname":"p.isTopicOfDiscussion","id":"i9YO8Z7TUEkxLONAPYgu9","vaultName":"public-notes"},"value":"tags.discursive","alias":"#discursive","position":{"start":{"line":4,"column":16,"offset":18},"end":{"line":4,"column":27,"offset":29},"indent":[]},"xvault":false,"to":{"fname":"tags.discursive"}},{"from":{"fname":"prdct.stride3d","id":"YEENs52Vldkdwe2jkkRpe","vaultName":"public-notes"},"type":"backlink","position":{"start":{"line":13,"column":3,"offset":284},"end":{"line":13,"column":28,"offset":309},"indent":[]},"value":"p.isTopicOfDiscussion"}],"anchors":{},"children":[],"parent":"pr50duvmwnfu5pf0zohcftk","data":{}}
