{"fname":"t.rec","stub":true,"vault":{"fsPath":"public-notes","remote":{"type":"git","url":"git@github.com:djradon/public-notes.git"},"name":"public-notes"},"schemaStub":false,"type":"note","updated":1727358098850,"created":1727358098850,"id":"kjeat2q6s9w0lf8nofr0578","desc":"","links":[],"anchors":{},"children":["lXSSyW451OBd08RzArzy1","9c0rn2sm63sr8msfjlypvf2","tIMrLK1OLBMJYqlNvbZlc","v73n9638s0izmsuak5lsdsq","tsuu694ed37u4mrq6hb4nku"],"parent":"QgQWvVXn3EJF7RptGkK2z","data":{},"title":"Rec"}
