{"id":"koLZgakQbzj4K6K72OWFw","title":"JSON","desc":"JavaScript Object Notation","updated":1723758324856,"created":1638128778554,"custom":{},"fname":"prdct.JSON","type":"note","vault":{"fsPath":"public-notes","remote":{"type":"git","url":"git@github.com:djradon/public-notes.git"},"name":"public-notes"},"contentHash":"1ab07883c0a46d02fb095285b0e2f3e8","links":[{"type":"wiki","from":{"fname":"prdct.JSON","id":"koLZgakQbzj4K6K72OWFw","vaultName":"public-notes"},"value":"p.instanceOf","position":{"start":{"line":2,"column":3,"offset":3},"end":{"line":2,"column":19,"offset":19},"indent":[]},"xvault":false,"sameFile":false,"to":{"fname":"p.instanceOf"}},{"type":"wiki","from":{"fname":"prdct.JSON","id":"koLZgakQbzj4K6K72OWFw","vaultName":"public-notes"},"value":"c.fileformat","position":{"start":{"line":2,"column":20,"offset":20},"end":{"line":2,"column":36,"offset":36},"indent":[]},"xvault":false,"sameFile":false,"to":{"fname":"c.fileformat"}},{"type":"wiki","from":{"fname":"prdct.JSON","id":"koLZgakQbzj4K6K72OWFw","vaultName":"public-notes"},"value":"c.dataformat","position":{"start":{"line":2,"column":37,"offset":37},"end":{"line":2,"column":53,"offset":53},"indent":[]},"xvault":false,"sameFile":false,"to":{"fname":"c.dataformat"}},{"type":"wiki","from":{"fname":"prdct.JSON","id":"koLZgakQbzj4K6K72OWFw","vaultName":"public-notes"},"value":"prdct.hjson","position":{"start":{"line":3,"column":12,"offset":65},"end":{"line":3,"column":27,"offset":80},"indent":[]},"xvault":false,"sameFile":false,"to":{"fname":"prdct.hjson"}},{"type":"wiki","from":{"fname":"prdct.JSON","id":"koLZgakQbzj4K6K72OWFw","vaultName":"public-notes"},"value":"prdct.yaml","position":{"start":{"line":7,"column":62,"offset":152},"end":{"line":7,"column":76,"offset":166},"indent":[]},"xvault":false,"sameFile":false,"to":{"fname":"prdct.yaml"}},{"type":"wiki","from":{"fname":"prdct.JSON","id":"koLZgakQbzj4K6K72OWFw","vaultName":"public-notes"},"value":"p.hasCriticism","position":{"start":{"line":9,"column":1,"offset":168},"end":{"line":9,"column":19,"offset":186},"indent":[]},"xvault":false,"sameFile":false,"to":{"fname":"p.hasCriticism"}},{"from":{"fname":"prdct.Graph-Commons","id":"fzEPnfPa7TAY6P0SpN9xp","vaultName":"public-notes"},"type":"backlink","position":{"start":{"line":14,"column":7,"offset":275},"end":{"line":14,"column":21,"offset":289},"indent":[]},"value":"prdct.json"},{"from":{"fname":"prdct.api-platform","id":"ps7m8l5a6xa52tbssq7f8pp","vaultName":"public-notes"},"type":"backlink","position":{"start":{"line":3,"column":27,"offset":55},"end":{"line":3,"column":41,"offset":69},"indent":[]},"value":"prdct.JSON"},{"from":{"fname":"prdct.json-rql","id":"colifmdgrpheolby8rpaunn","vaultName":"public-notes"},"type":"backlink","position":{"start":{"line":11,"column":8,"offset":428},"end":{"line":11,"column":22,"offset":442},"indent":[]},"value":"prdct.json"},{"from":{"fname":"prdct.yaml","id":"36h5cstfnd55cap4r9jcxlb","vaultName":"public-notes"},"type":"backlink","position":{"start":{"line":8,"column":8,"offset":78},"end":{"line":8,"column":22,"offset":92},"indent":[]},"value":"prdct.json"}],"anchors":{"cons":{"type":"header","text":"Cons","value":"cons","line":11,"column":0,"depth":2}},"children":["nu3azi864fsenxktknnqldj","lvfiph970za1benbpsl2imd"],"parent":"6q10hkz3zuvnueqa9slqqmu","data":{}}
