{"id":"n8l1n464e4cgr3t6gcaw6s8","title":"Free Tier","desc":"","updated":1696048646122,"created":1696048625435,"custom":{},"fname":"tags.free-tier","type":"note","vault":{"fsPath":"public-notes","remote":{"type":"git","url":"git@github.com:djradon/public-notes.git"},"name":"public-notes"},"contentHash":"494b3d836e1958073a823aa074804d44","links":[{"type":"wiki","from":{"fname":"tags.free-tier","id":"n8l1n464e4cgr3t6gcaw6s8","vaultName":"public-notes"},"value":"p.coreferences","position":{"start":{"line":2,"column":3,"offset":3},"end":{"line":2,"column":21,"offset":21},"indent":[]},"xvault":false,"sameFile":false,"to":{"fname":"p.coreferences"}},{"type":"wiki","from":{"fname":"tags.free-tier","id":"n8l1n464e4cgr3t6gcaw6s8","vaultName":"public-notes"},"value":"t.biz.free-tier","position":{"start":{"line":2,"column":22,"offset":22},"end":{"line":2,"column":41,"offset":41},"indent":[]},"xvault":false,"sameFile":false,"to":{"fname":"t.biz.free-tier"}},{"from":{"fname":"prdct.nats","id":"iypvlwhcbuwo79fm2uayixf","vaultName":"public-notes"},"type":"backlink","position":{"start":{"line":21,"column":20,"offset":1150},"end":{"line":21,"column":30,"offset":1160},"indent":[]},"value":"tags.free-tier"}],"anchors":{},"children":[],"parent":"VdoOKc3Rq9WmIDPW3ifi0","data":{}}
