{"id":"qihqgvf2nguyqaj8cywpwvf","title":"React Map Gl","desc":"","updated":1699990425377,"created":1699990425377,"custom":{},"fname":"prdct.react-map-gl","type":"note","vault":{"fsPath":"public-notes","remote":{"type":"git","url":"git@github.com:djradon/public-notes.git"},"name":"public-notes"},"contentHash":"a0b106c107aa300ea37203e9e3a25c8b","links":[{"from":{"fname":"prdct.h3","id":"eqpfbn6ppca6xxa2dpyjmuk","vaultName":"public-notes"},"type":"backlink","position":{"start":{"line":41,"column":14,"offset":1828},"end":{"line":41,"column":36,"offset":1850},"indent":[]},"value":"prdct.react-map-gl"}],"anchors":{},"children":[],"parent":"6q10hkz3zuvnueqa9slqqmu","data":{}}
