{"id":"qp7znmise7kdx3xz2btzkpj","title":"Relinq","desc":"create full-featured LINQ providers","updated":1709139978890,"created":1709139961021,"custom":{},"fname":"prdct.relinq","type":"note","vault":{"fsPath":"public-notes","remote":{"type":"git","url":"git@github.com:djradon/public-notes.git"},"name":"public-notes"},"contentHash":"a14dc58ddb147f6de5550ff4f10bb084","links":[{"from":{"fname":"prdct.trinity-rdf","id":"3chfiteid1962f7jy9io3rx","vaultName":"public-notes"},"type":"backlink","position":{"start":{"line":5,"column":33,"offset":130},"end":{"line":5,"column":49,"offset":146},"indent":[]},"value":"prdct.relinq"}],"anchors":{},"children":[],"parent":"6q10hkz3zuvnueqa9slqqmu","data":{}}
