{"id":"r5y3bpskszo7gva6cj4kirp","title":"Ian Bogost","desc":"","updated":1727178919519,"created":1727178919519,"custom":{},"fname":"user.ian-bogost","type":"note","vault":{"fsPath":"public-notes","remote":{"type":"git","url":"git@github.com:djradon/public-notes.git"},"name":"public-notes"},"contentHash":"0908bdc5188e27afc0be101f4fe68bda","links":[{"from":{"fname":"ar.atlantic.video-games-are-better-without-stories","id":"b1h0j78mhw4zmcvqtc8yr1f","vaultName":"public-notes"},"type":"backlink","position":{"start":{"line":3,"column":11,"offset":96},"end":{"line":3,"column":22,"offset":107},"indent":[]},"value":"user.ian-bogost"},{"from":{"fname":"ar.newyorker.hamlet-on-the-holodeck-twenty-years-later","id":"woy1bh3hma4kghubboql6di","vaultName":"public-notes"},"type":"backlink","position":{"start":{"line":14,"column":37,"offset":1775},"end":{"line":14,"column":48,"offset":1786},"indent":[]},"value":"user.ian-bogost"},{"from":{"fname":"blogs.carpe-noctem.2024-09-27-introducing-carpe-noctem","id":"4ndmblmh5zuf09cx5rgw0k1","vaultName":"public-notes"},"type":"backlink","position":{"start":{"line":116,"column":17,"offset":11514},"end":{"line":116,"column":36,"offset":11533},"indent":[]},"value":"user.ian-bogost"}],"anchors":{},"children":[],"parent":"g24de3ikvaqmy6bp4m223t0","data":{}}
