{"id":"rltz8y68wxb51hmwpktyz8u","title":"moment.js","desc":"","updated":1674535718590,"created":1674535710593,"custom":{},"fname":"prdct.momentjs","type":"note","vault":{"fsPath":"public-notes","remote":{"type":"git","url":"git@github.com:djradon/public-notes.git"},"name":"public-notes"},"contentHash":"4858a49a6f203b3592d0c126534628d5","links":[{"from":{"fname":"prdct.luxon","id":"jo0hr8awuvs4pvl2cpvsixq","vaultName":"public-notes"},"type":"backlink","position":{"start":{"line":5,"column":19,"offset":97},"end":{"line":5,"column":37,"offset":115},"indent":[]},"value":"prdct.momentjs"}],"anchors":{},"children":[],"parent":"6q10hkz3zuvnueqa9slqqmu","data":{}}
