{"id":"ruSrmZTjVR8HfKXAFsAcH","title":"provided","desc":"an org or agent can provide a service, product, or solution","updated":1671319950993,"created":1641359700318,"custom":{},"fname":"p.provided","type":"note","vault":{"fsPath":"public-notes","remote":{"type":"git","url":"git@github.com:djradon/public-notes.git"},"name":"public-notes"},"contentHash":"3722cd7a8c7a21456c27b04c859c3a0e","links":[{"type":"wiki","from":{"fname":"p.provided","id":"ruSrmZTjVR8HfKXAFsAcH","vaultName":"public-notes"},"value":"c.sphere","position":{"start":{"line":3,"column":3,"offset":4},"end":{"line":3,"column":15,"offset":16},"indent":[]},"xvault":false,"sameFile":false,"to":{"fname":"c.sphere"}},{"type":"wiki","from":{"fname":"p.provided","id":"ruSrmZTjVR8HfKXAFsAcH","vaultName":"public-notes"},"value":"tags.product-management","alias":"#product-management","position":{"start":{"line":3,"column":16,"offset":17},"end":{"line":3,"column":35,"offset":36},"indent":[]},"xvault":false,"to":{"fname":"tags.product-management"}},{"from":{"fname":"org.granthika","id":"9gtfyox866j3egy1x98b0yn","vaultName":"public-notes"},"type":"backlink","position":{"start":{"line":3,"column":3,"offset":4},"end":{"line":3,"column":17,"offset":18},"indent":[]},"value":"p.provided"},{"from":{"fname":"org.lucid","id":"m0h44zwxdPZ6431y4xYAz","vaultName":"public-notes"},"type":"backlink","position":{"start":{"line":4,"column":3,"offset":5},"end":{"line":4,"column":17,"offset":19},"indent":[]},"value":"p.provided"},{"from":{"fname":"org.rti","id":"6muhc760qio322tfkemw25p","vaultName":"public-notes"},"type":"backlink","position":{"start":{"line":3,"column":3,"offset":4},"end":{"line":3,"column":17,"offset":18},"indent":[]},"value":"p.provided"},{"from":{"fname":"org.viev","id":"2BDVQBPbMrKE3KJzH997S","vaultName":"public-notes"},"type":"backlink","position":{"start":{"line":4,"column":3,"offset":41},"end":{"line":4,"column":17,"offset":55},"indent":[]},"value":"p.provided"}],"anchors":{},"children":[],"parent":"pr50duvmwnfu5pf0zohcftk","data":{}}
