{"id":"s4zfzmitb9w3enipj22ma71","title":"Time","desc":"","updated":1725989093040,"created":1725989093040,"custom":{},"fname":"tags.time","type":"note","vault":{"fsPath":"public-notes","remote":{"type":"git","url":"git@github.com:djradon/public-notes.git"},"name":"public-notes"},"contentHash":"27daefd7eee4e72d6307b122d41d6c0a","links":[{"from":{"fname":"video.twilight-zone.s01e08-time-enough-at-last","id":"5otvouu5ddol55s1g9hjece","vaultName":"public-notes"},"type":"backlink","position":{"start":{"line":4,"column":29,"offset":85},"end":{"line":4,"column":34,"offset":90},"indent":[]},"value":"tags.time"}],"anchors":{},"children":[],"parent":"VdoOKc3Rq9WmIDPW3ifi0","data":{}}
