{"id":"soywp1lm9api3lfx2zcis3i","title":"FAIR Data","desc":"Findable, Accessible, Interoperable, and Reusable","updated":1725381963561,"created":1717523325360,"custom":{},"fname":"t.cs.data.fair","type":"note","vault":{"fsPath":"public-notes","remote":{"type":"git","url":"git@github.com:djradon/public-notes.git"},"name":"public-notes"},"contentHash":"55563e9ec60d59c1ea6ba3092018c0ee","links":[{"from":{"fname":"prdct.ontouml-models","id":"mfv768njrditddvw8kjhbfh","vaultName":"public-notes"},"type":"backlink","position":{"start":{"line":3,"column":12,"offset":52},"end":{"line":3,"column":30,"offset":70},"indent":[]},"value":"t.cs.data.fair"}],"anchors":{},"children":[],"parent":"2b3uc1rlf8uuhp1wiuavmr9","data":{}}
