{"id":"t42nut6r3spxr2fh331u91f","title":"Material Web","desc":"Google’s component library for building applications that work in any web framework.","updated":1707778699941,"created":1707778651197,"custom":{},"fname":"prdct.material-web","type":"note","vault":{"fsPath":"public-notes","remote":{"type":"git","url":"git@github.com:djradon/public-notes.git"},"name":"public-notes"},"contentHash":"fba286bfc33e2a0a67f8dabe78984b97","links":[],"anchors":{},"children":[],"parent":"6q10hkz3zuvnueqa9slqqmu","data":{}}
