{"id":"u5dwr5q2k3yk1gk1p1yfav6","title":"Cyber Risk","desc":"","updated":1666885695359,"created":1666885695359,"custom":{},"fname":"t.cs.security.cyber-risk","type":"note","vault":{"fsPath":"public-notes","remote":{"type":"git","url":"git@github.com:djradon/public-notes.git"},"name":"public-notes"},"contentHash":"4be8e60d89f47996170f5fea15d5f21e","links":[{"from":{"fname":"event.2022.cybersecurity-summit.darktrace-presentation","id":"gy1mruf6m39rdtu67hfy4ku","vaultName":"public-notes"},"type":"backlink","position":{"start":{"line":8,"column":19,"offset":193},"end":{"line":8,"column":47,"offset":221},"indent":[]},"value":"t.cs.security.cyber-risk"}],"anchors":{},"children":[],"parent":"s2btZTlcvhcrlGunPlgvw","data":{}}
