{"id":"u69ohenrjzegyb4ta4bp07j","title":"Basic Formal Ontology","desc":"a small, upper-level, realist, bicategorial ontology that is designed for use in supporting information retrieval, analysis and integration in scientific and other domains","updated":1730762652373,"created":1696610915530,"custom":{},"fname":"prdct.basic-formal-ontology","type":"note","vault":{"fsPath":"public-notes","remote":{"type":"git","url":"git@github.com:djradon/public-notes.git"},"name":"public-notes"},"contentHash":"c5787e9ad079bf6cc3e0acf2ef1eb4ad","links":[{"type":"wiki","from":{"fname":"prdct.basic-formal-ontology","id":"u69ohenrjzegyb4ta4bp07j","vaultName":"public-notes"},"value":"c.ontology.upper","position":{"start":{"line":2,"column":3,"offset":3},"end":{"line":2,"column":23,"offset":23},"indent":[]},"xvault":false,"sameFile":false,"to":{"fname":"c.ontology.upper"}},{"type":"wiki","from":{"fname":"prdct.basic-formal-ontology","id":"u69ohenrjzegyb4ta4bp07j","vaultName":"public-notes"},"value":"tags.docs","alias":"#docs","position":{"start":{"line":5,"column":3,"offset":179},"end":{"line":5,"column":8,"offset":184},"indent":[]},"xvault":false,"to":{"fname":"tags.docs"}},{"type":"wiki","from":{"fname":"prdct.basic-formal-ontology","id":"u69ohenrjzegyb4ta4bp07j","vaultName":"public-notes"},"value":"tags.similar","alias":"#similar","position":{"start":{"line":6,"column":3,"offset":228},"end":{"line":6,"column":11,"offset":236},"indent":[]},"xvault":false,"to":{"fname":"tags.similar"}},{"type":"wiki","from":{"fname":"prdct.basic-formal-ontology","id":"u69ohenrjzegyb4ta4bp07j","vaultName":"public-notes"},"value":"prdct.gist","position":{"start":{"line":6,"column":12,"offset":237},"end":{"line":6,"column":26,"offset":251},"indent":[]},"xvault":false,"sameFile":false,"to":{"fname":"prdct.gist"}},{"type":"wiki","from":{"fname":"prdct.basic-formal-ontology","id":"u69ohenrjzegyb4ta4bp07j","vaultName":"public-notes"},"value":"prdct.common-core-ontologies","position":{"start":{"line":7,"column":12,"offset":263},"end":{"line":7,"column":44,"offset":295},"indent":[]},"xvault":false,"sameFile":false,"to":{"fname":"prdct.common-core-ontologies"}},{"type":"wiki","from":{"fname":"prdct.basic-formal-ontology","id":"u69ohenrjzegyb4ta4bp07j","vaultName":"public-notes"},"value":"ar.bfo-2-0-specification-and-users-guide","position":{"start":{"line":65,"column":3,"offset":3942},"end":{"line":65,"column":47,"offset":3986},"indent":[]},"xvault":false,"sameFile":false,"to":{"fname":"ar.bfo-2-0-specification-and-users-guide"}},{"type":"wiki","from":{"fname":"prdct.basic-formal-ontology","id":"u69ohenrjzegyb4ta4bp07j","vaultName":"public-notes"},"value":"ar.basic-formal-ontology-july-2023","position":{"start":{"line":67,"column":3,"offset":4089},"end":{"line":67,"column":41,"offset":4127},"indent":[]},"xvault":false,"sameFile":false,"to":{"fname":"ar.basic-formal-ontology-july-2023"}},{"type":"wiki","from":{"fname":"prdct.basic-formal-ontology","id":"u69ohenrjzegyb4ta4bp07j","vaultName":"public-notes"},"value":"prdct.bfo-classifier","position":{"start":{"line":68,"column":3,"offset":4130},"end":{"line":68,"column":27,"offset":4154},"indent":[]},"xvault":false,"sameFile":false,"to":{"fname":"prdct.bfo-classifier"}},{"type":"wiki","from":{"fname":"prdct.basic-formal-ontology","id":"u69ohenrjzegyb4ta4bp07j","vaultName":"public-notes"},"value":"book.building-ontologies-with-basic-formal-ontology","position":{"start":{"line":69,"column":3,"offset":4157},"end":{"line":69,"column":58,"offset":4212},"indent":[]},"xvault":false,"sameFile":false,"to":{"fname":"book.building-ontologies-with-basic-formal-ontology"}},{"type":"wiki","from":{"fname":"prdct.basic-formal-ontology","id":"u69ohenrjzegyb4ta4bp07j","vaultName":"public-notes"},"value":"ar.foundational-ontologies-in-action","position":{"start":{"line":74,"column":3,"offset":4277},"end":{"line":74,"column":43,"offset":4317},"indent":[]},"xvault":false,"sameFile":false,"to":{"fname":"ar.foundational-ontologies-in-action"}},{"type":"wiki","from":{"fname":"prdct.basic-formal-ontology","id":"u69ohenrjzegyb4ta4bp07j","vaultName":"public-notes"},"value":"community.google-groups.bfo-discuss.entity-to-particular","position":{"start":{"line":77,"column":3,"offset":4633},"end":{"line":77,"column":63,"offset":4693},"indent":[]},"xvault":false,"sameFile":false,"to":{"fname":"community.google-groups.bfo-discuss.entity-to-particular"}},{"type":"ref","from":{"fname":"prdct.basic-formal-ontology","id":"u69ohenrjzegyb4ta4bp07j","vaultName":"public-notes"},"value":"prdct.gist","position":{"start":{"line":61,"column":1,"offset":3767},"end":{"line":61,"column":158,"offset":3924},"indent":[]},"xvault":false,"to":{"fname":"prdct.gist","anchorHeader":"comparison-gist-council-12-1-22---gistbfo-comparison-with-dylan-abney"}},{"from":{"fname":"ar.a-comparison-of-upper-ontologies","id":"9t4gwbk0fqhawfob2u74pxl","vaultName":"public-notes"},"type":"backlink","position":{"start":{"line":4,"column":15,"offset":155},"end":{"line":4,"column":46,"offset":186},"indent":[]},"value":"prdct.basic-formal-ontology"},{"from":{"fname":"ar.classifying-processes","id":"03g5n90pq0fbkoqz7yi9l2e","vaultName":"public-notes"},"type":"backlink","position":{"start":{"line":3,"column":29,"offset":101},"end":{"line":3,"column":60,"offset":132},"indent":[]},"value":"prdct.basic-formal-ontology"},{"from":{"fname":"ar.foundational-ontologies-from-theory-to-practice-and-back","id":"h00qd3mljukg0lhqh3fi2lf","vaultName":"public-notes"},"type":"backlink","position":{"start":{"line":12,"column":166,"offset":720},"end":{"line":12,"column":197,"offset":751},"indent":[]},"value":"prdct.basic-formal-ontology"},{"from":{"fname":"ar.foundational-ontologies-in-action","id":"ghlsg7kgdqzmhsebsf4df3m","vaultName":"public-notes"},"type":"backlink","position":{"start":{"line":7,"column":13,"offset":282},"end":{"line":7,"column":44,"offset":313},"indent":[]},"value":"prdct.basic-formal-ontology"},{"from":{"fname":"ar.ontology-infrastructure-for-the-semantic-web","id":"wiw9qpfatgigmxehpghorb4","vaultName":"public-notes"},"type":"backlink","position":{"start":{"line":4,"column":43,"offset":195},"end":{"line":4,"column":74,"offset":226},"indent":[]},"value":"prdct.basic-formal-ontology"},{"from":{"fname":"ar.representing-literary-characters-and-their-attributes-in-an-ontology","id":"3soxx69xxsbswz4gkhc4esq","vaultName":"public-notes"},"type":"backlink","position":{"start":{"line":3,"column":83,"offset":124},"end":{"line":3,"column":114,"offset":155},"indent":[]},"value":"prdct.basic-formal-ontology"},{"from":{"fname":"ar.roles-and-their-three-facets-a-foundational-perspective","id":"g4mcfss08k8e4n3d04hgh3w","vaultName":"public-notes"},"type":"backlink","position":{"start":{"line":7,"column":532,"offset":635},"end":{"line":7,"column":563,"offset":666},"indent":[]},"value":"prdct.basic-formal-ontology"},{"from":{"fname":"ar.some-open-issues-after-twenty-years-of-formal-ontology","id":"nmgqmbzh6ftaa7jj2woieqa","vaultName":"public-notes"},"type":"backlink","position":{"start":{"line":24,"column":5,"offset":2984},"end":{"line":24,"column":36,"offset":3015},"indent":[]},"value":"prdct.basic-formal-ontology"},{"from":{"fname":"prdct.common-core-ontologies","id":"zpjzyrw9areg7unx2h1pkbz","vaultName":"public-notes"},"type":"backlink","position":{"start":{"line":5,"column":12,"offset":132},"end":{"line":5,"column":43,"offset":163},"indent":[]},"value":"prdct.basic-formal-ontology"},{"from":{"fname":"prdct.ikw-graphengine","id":"vqzlwz59px5e1zwv35yrkpq","vaultName":"public-notes"},"type":"backlink","position":{"start":{"line":7,"column":3,"offset":98},"end":{"line":7,"column":34,"offset":129},"indent":[]},"value":"prdct.basic-formal-ontology"},{"from":{"fname":"prdct.literary-theme-ontology","id":"fcd1ugyroyf4np1s9mhndnz","vaultName":"public-notes"},"type":"backlink","position":{"start":{"line":3,"column":13,"offset":63},"end":{"line":3,"column":44,"offset":94},"indent":[]},"value":"prdct.basic-formal-ontology"},{"from":{"fname":"prdct.mental-functioning-ontology","id":"5vzi7i03r07xsckafgyidog","vaultName":"public-notes"},"type":"backlink","position":{"start":{"line":4,"column":12,"offset":123},"end":{"line":4,"column":43,"offset":154},"indent":[]},"value":"prdct.basic-formal-ontology"},{"from":{"fname":"prdct.open-biological-ontology","id":"dw5wof2vpyug5q45cyfjta2","vaultName":"public-notes"},"type":"backlink","position":{"start":{"line":2,"column":12,"offset":12},"end":{"line":2,"column":43,"offset":43},"indent":[]},"value":"prdct.basic-formal-ontology"},{"from":{"fname":"prdct.sumo","id":"r7wmmwwaws15llja6y5ng7h","vaultName":"public-notes"},"type":"backlink","position":{"start":{"line":40,"column":3,"offset":2046},"end":{"line":40,"column":34,"offset":2077},"indent":[]},"value":"prdct.basic-formal-ontology"},{"from":{"fname":"t.km.ontology","id":"r4s8HiOEaLW0Z3lvFUvHL","vaultName":"public-notes"},"type":"backlink","position":{"start":{"line":38,"column":3,"offset":1250},"end":{"line":38,"column":34,"offset":1281},"indent":[]},"value":"prdct.basic-formal-ontology"}],"anchors":{"description":{"type":"header","text":"Description","value":"description","line":20,"column":0,"depth":2},"issues":{"type":"header","text":"Issues","value":"issues","line":25,"column":0,"depth":2},"attributes":{"type":"header","text":"Attributes","value":"attributes","line":59,"column":0,"depth":2},"bfo2-reference":{"type":"header","text":"BFO2 Reference","value":"bfo2-reference","line":65,"column":0,"depth":2},"resources":{"type":"header","text":"Resources","value":"resources","line":72,"column":0,"depth":2},"references":{"type":"header","text":"References","value":"references","line":80,"column":0,"depth":2}},"children":["v9zvnya3m77skyenebfzml6"],"parent":"6q10hkz3zuvnueqa9slqqmu","data":{}}
