{"id":"u96apgyo1muyx1234mrpa7l","title":"Web Editor","desc":"","updated":1750865086149,"created":1750865012138,"custom":{},"fname":"c.software.web.editor","type":"note","vault":{"fsPath":"public-notes","remote":{"type":"git","url":"git@github.com:djradon/public-notes.git"},"name":"public-notes"},"contentHash":"e31c6de0a5041d72242c0565040e9987","links":[{"from":{"fname":"prdct.ace-editor","id":"zesneysh4r19pea5s4jhyow","vaultName":"public-notes"},"type":"backlink","position":{"start":{"line":3,"column":3,"offset":24},"end":{"line":3,"column":28,"offset":49},"indent":[]},"value":"c.software.web.editor"},{"from":{"fname":"prdct.codemirror","id":"6j57rafyg4gpzr6fkj6gfwy","vaultName":"public-notes"},"type":"backlink","position":{"start":{"line":3,"column":3,"offset":29},"end":{"line":3,"column":28,"offset":54},"indent":[]},"value":"c.software.web.editor"},{"from":{"fname":"prdct.monaco-editor","id":"jmrg0saebd43eovn80uvwle","vaultName":"public-notes"},"type":"backlink","position":{"start":{"line":3,"column":30,"offset":75},"end":{"line":3,"column":55,"offset":100},"indent":[]},"value":"c.software.web.editor"}],"anchors":{"reviews":{"type":"header","text":"Reviews","value":"reviews","line":9,"column":0,"depth":2}},"children":[],"parent":"heozpyzjpp2pwusx01g65g2","data":{}}
