{"id":"u9du3ro2al7vsk6pybvkoh9","title":"Noosphere","desc":"a worldwide decentralized repository for thought, belonging to everybody. A decentralized graph, where you own thoughts, and have agency to move your data between services and apps.","updated":1714622571078,"created":1653256852662,"custom":{},"fname":"prdct.noosphere","type":"note","vault":{"fsPath":"public-notes","remote":{"type":"git","url":"git@github.com:djradon/public-notes.git"},"name":"public-notes"},"contentHash":"2753bf4f5a85e102771d7c9df1c7eedb","links":[{"type":"wiki","from":{"fname":"prdct.noosphere","id":"u9du3ro2al7vsk6pybvkoh9","vaultName":"public-notes"},"value":"org.subconscious","position":{"start":{"line":3,"column":15,"offset":47},"end":{"line":3,"column":35,"offset":67},"indent":[]},"xvault":false,"sameFile":false,"to":{"fname":"org.subconscious"}},{"type":"wiki","from":{"fname":"prdct.noosphere","id":"u9du3ro2al7vsk6pybvkoh9","vaultName":"public-notes"},"value":"prdct.decentralized-identifiers","position":{"start":{"line":6,"column":5,"offset":141},"end":{"line":6,"column":40,"offset":176},"indent":[]},"xvault":false,"sameFile":false,"to":{"fname":"prdct.decentralized-identifiers"}},{"type":"wiki","from":{"fname":"prdct.noosphere","id":"u9du3ro2al7vsk6pybvkoh9","vaultName":"public-notes"},"value":"prdct.cid","position":{"start":{"line":7,"column":5,"offset":181},"end":{"line":7,"column":18,"offset":194},"indent":[]},"xvault":false,"sameFile":false,"to":{"fname":"prdct.cid"}},{"type":"wiki","from":{"fname":"prdct.noosphere","id":"u9du3ro2al7vsk6pybvkoh9","vaultName":"public-notes"},"value":"t.cs.distributed.hash-table","position":{"start":{"line":8,"column":5,"offset":199},"end":{"line":8,"column":36,"offset":230},"indent":[]},"xvault":false,"sameFile":false,"to":{"fname":"t.cs.distributed.hash-table"}},{"type":"wiki","from":{"fname":"prdct.noosphere","id":"u9du3ro2al7vsk6pybvkoh9","vaultName":"public-notes"},"value":"prdct.libp2p","position":{"start":{"line":9,"column":13,"offset":243},"end":{"line":9,"column":29,"offset":259},"indent":[]},"xvault":false,"sameFile":false,"to":{"fname":"prdct.libp2p"}},{"type":"wiki","from":{"fname":"prdct.noosphere","id":"u9du3ro2al7vsk6pybvkoh9","vaultName":"public-notes"},"value":"prdct.decentralized-identifiers","alias":"DIDs","position":{"start":{"line":15,"column":118,"offset":425},"end":{"line":15,"column":158,"offset":465},"indent":[]},"xvault":false,"sameFile":false,"to":{"fname":"prdct.decentralized-identifiers"}},{"type":"wiki","from":{"fname":"prdct.noosphere","id":"u9du3ro2al7vsk6pybvkoh9","vaultName":"public-notes"},"value":"prdct.cid","position":{"start":{"line":19,"column":180,"offset":787},"end":{"line":19,"column":193,"offset":800},"indent":[]},"xvault":false,"sameFile":false,"to":{"fname":"prdct.cid"}},{"type":"wiki","from":{"fname":"prdct.noosphere","id":"u9du3ro2al7vsk6pybvkoh9","vaultName":"public-notes"},"value":"prdct.ipld","position":{"start":{"line":25,"column":41,"offset":1252},"end":{"line":25,"column":55,"offset":1266},"indent":[]},"xvault":false,"sameFile":false,"to":{"fname":"prdct.ipld"}},{"type":"wiki","from":{"fname":"prdct.noosphere","id":"u9du3ro2al7vsk6pybvkoh9","vaultName":"public-notes"},"value":"prdct.ucan","alias":"UCAN","position":{"start":{"line":33,"column":92,"offset":2216},"end":{"line":33,"column":111,"offset":2235},"indent":[]},"xvault":false,"sameFile":false,"to":{"fname":"prdct.ucan"}},{"type":"wiki","from":{"fname":"prdct.noosphere","id":"u9du3ro2al7vsk6pybvkoh9","vaultName":"public-notes"},"value":"t.cs.distributed.hash-table","position":{"start":{"line":35,"column":340,"offset":2861},"end":{"line":35,"column":371,"offset":2892},"indent":[]},"xvault":false,"sameFile":false,"to":{"fname":"t.cs.distributed.hash-table"}},{"type":"wiki","from":{"fname":"prdct.noosphere","id":"u9du3ro2al7vsk6pybvkoh9","vaultName":"public-notes"},"value":"ar.substack.subconscious.the-minimal-definition-of-user-agency","position":{"start":{"line":43,"column":3,"offset":3137},"end":{"line":43,"column":69,"offset":3203},"indent":[]},"xvault":false,"sameFile":false,"to":{"fname":"ar.substack.subconscious.the-minimal-definition-of-user-agency"}},{"from":{"fname":"prdct.subconscious","id":"k13y6rrotb17n2s1ob1ndna","vaultName":"public-notes"},"type":"backlink","position":{"start":{"line":7,"column":5,"offset":138},"end":{"line":7,"column":24,"offset":157},"indent":[]},"value":"prdct.noosphere"},{"from":{"fname":"prdct.ucan","id":"8h6vqvqt1mb629yktcb1eoq","vaultName":"public-notes"},"type":"backlink","position":{"start":{"line":6,"column":5,"offset":122},"end":{"line":6,"column":24,"offset":141},"indent":[]},"value":"prdct.noosphere"},{"from":{"fname":"ar.substack.subconscious.decentralization","id":"5efwjmjvaaasfsv4sg6sr67","vaultName":"public-notes"},"type":"backlink","position":{"start":{"line":21,"column":139,"offset":895},"end":{"line":21,"column":158,"offset":914},"indent":[]},"value":"prdct.noosphere"}],"anchors":{"description":{"type":"header","text":"Description","value":"description","line":20,"column":0,"depth":2},"public-key-infrastructure":{"type":"header","text":"Public key infrastructure","value":"public-key-infrastructure","line":22,"column":0,"depth":3},"content-addressing":{"type":"header","text":"Content Addressing","value":"content-addressing","line":26,"column":0,"depth":3},"immutable-data":{"type":"header","text":"Immutable data","value":"immutable-data","line":32,"column":0,"depth":3},"p2p-routing-and-discovery":{"type":"header","text":"P2P routing and discovery","value":"p2p-routing-and-discovery","line":38,"column":0,"depth":3},"thoughts":{"type":"header","text":"Thoughts","value":"thoughts","line":46,"column":0,"depth":2},"references":{"type":"header","text":"References","value":"references","line":50,"column":0,"depth":2}},"children":[],"parent":"6q10hkz3zuvnueqa9slqqmu","data":{}}
