{"id":"uZJM5HBOQkKJMEqqz3fgR","title":"The Three Systems beneath Network Effects","desc":"","updated":1638944167954,"created":1638942180854,"custom":{},"fname":"email.the-three-systems-beneath-network-effects","type":"note","vault":{"fsPath":"public-notes","remote":{"type":"git","url":"git@github.com:djradon/public-notes.git"},"name":"public-notes"},"contentHash":"12a7b0105b2ec703d681787c7749eb4f","links":[{"from":{"fname":"ar.every.the-three-systems-beneath-network-effects","id":"cl1EoUjd0xXP6tmydFtNG","vaultName":"public-notes"},"type":"backlink","position":{"start":{"line":2,"column":9,"offset":9},"end":{"line":2,"column":60,"offset":60},"indent":[]},"value":"email.the-three-systems-beneath-network-effects"}],"anchors":{"the-three-systems":{"type":"header","text":"The Three Systems","value":"the-three-systems","line":10,"column":0,"depth":1},"chapter-18the-trio-of-forces":{"type":"header","text":"Chapter 18: The Trio of Forces","value":"chapter-18the-trio-of-forces","line":58,"column":0,"depth":2},"three-systems-underlying-the-network-effect":{"type":"header","text":"Three Systems Underlying the Network Effect","value":"three-systems-underlying-the-network-effect","line":68,"column":0,"depth":2},"the-growth-accounting-equation":{"type":"header","text":"The Growth Accounting Equation","value":"the-growth-accounting-equation","line":78,"column":0,"depth":2}},"children":[],"parent":"dfk38hodq90wterkjm41g6d","data":{}}
