{"id":"x219kze2gk6lbvyfa7ftlv5","title":"Ontomedia Creating an Ontology for Marking up the Contents of Heterogeneous Media","desc":"","updated":1730645843820,"created":1710828494951,"custom":{},"fname":"ar.ontomedia-creating-an-ontology-for-marking-up-the-contents-of-heterogeneous-media","type":"note","vault":{"fsPath":"public-notes","remote":{"type":"git","url":"git@github.com:djradon/public-notes.git"},"name":"public-notes"},"contentHash":"1b0fc7fdd0b552532cb8a3349e5e814d","links":[{"type":"wiki","from":{"fname":"ar.ontomedia-creating-an-ontology-for-marking-up-the-contents-of-heterogeneous-media","id":"x219kze2gk6lbvyfa7ftlv5","vaultName":"public-notes"},"value":"prdct.cidoc-crm","position":{"start":{"line":3,"column":12,"offset":74},"end":{"line":3,"column":31,"offset":93},"indent":[]},"xvault":false,"sameFile":false,"to":{"fname":"prdct.cidoc-crm"}},{"type":"wiki","from":{"fname":"ar.ontomedia-creating-an-ontology-for-marking-up-the-contents-of-heterogeneous-media","id":"x219kze2gk6lbvyfa7ftlv5","vaultName":"public-notes"},"value":"prdct.ontomedia","position":{"start":{"line":3,"column":32,"offset":94},"end":{"line":3,"column":51,"offset":113},"indent":[]},"xvault":false,"sameFile":false,"to":{"fname":"prdct.ontomedia"}},{"type":"wiki","from":{"fname":"ar.ontomedia-creating-an-ontology-for-marking-up-the-contents-of-heterogeneous-media","id":"x219kze2gk6lbvyfa7ftlv5","vaultName":"public-notes"},"value":"user.faith-lawrence","alias":"@faith-lawrence","position":{"start":{"line":5,"column":12,"offset":138},"end":{"line":5,"column":27,"offset":153},"indent":[]},"xvault":false,"to":{"fname":"user.faith-lawrence"}},{"type":"wiki","from":{"fname":"ar.ontomedia-creating-an-ontology-for-marking-up-the-contents-of-heterogeneous-media","id":"x219kze2gk6lbvyfa7ftlv5","vaultName":"public-notes"},"value":"user.monica-schraefel","alias":"@monica-schraefel","position":{"start":{"line":5,"column":28,"offset":154},"end":{"line":5,"column":45,"offset":171},"indent":[]},"xvault":false,"to":{"fname":"user.monica-schraefel"}},{"type":"wiki","from":{"fname":"ar.ontomedia-creating-an-ontology-for-marking-up-the-contents-of-heterogeneous-media","id":"x219kze2gk6lbvyfa7ftlv5","vaultName":"public-notes"},"value":"prdct.swoogle","position":{"start":{"line":9,"column":12,"offset":199},"end":{"line":9,"column":29,"offset":216},"indent":[]},"xvault":false,"sameFile":false,"to":{"fname":"prdct.swoogle"}},{"type":"wiki","from":{"fname":"ar.ontomedia-creating-an-ontology-for-marking-up-the-contents-of-heterogeneous-media","id":"x219kze2gk6lbvyfa7ftlv5","vaultName":"public-notes"},"value":"ar.narrative-as-a-form-of-knowledge-transfer-narrative-theory-and-semantics","position":{"start":{"line":19,"column":54,"offset":597},"end":{"line":19,"column":133,"offset":676},"indent":[]},"xvault":false,"sameFile":false,"to":{"fname":"ar.narrative-as-a-form-of-knowledge-transfer-narrative-theory-and-semantics"}},{"type":"wiki","from":{"fname":"ar.ontomedia-creating-an-ontology-for-marking-up-the-contents-of-heterogeneous-media","id":"x219kze2gk6lbvyfa7ftlv5","vaultName":"public-notes"},"value":"ar.amateur-fiction-online-the-web-of-community-trust","alias":"Amateur fiction online - the web of community trust","position":{"start":{"line":20,"column":40,"offset":780},"end":{"line":20,"column":148,"offset":888},"indent":[]},"xvault":false,"sameFile":false,"to":{"fname":"ar.amateur-fiction-online-the-web-of-community-trust"}},{"from":{"fname":"prdct.ontomedia","id":"twccw0iaye1yncgudxrr8a1","vaultName":"public-notes"},"type":"backlink","position":{"start":{"line":42,"column":3,"offset":2944},"end":{"line":42,"column":91,"offset":3032},"indent":[]},"value":"ar.ontomedia-creating-an-ontology-for-marking-up-the-contents-of-heterogeneous-media"}],"anchors":{"highlights":{"type":"header","text":"Highlights","value":"highlights","line":15,"column":0,"depth":2},"references":{"type":"header","text":"References","value":"references","line":25,"column":0,"depth":2}},"children":[],"parent":"7272514wvvn78ppl0gxbz1o","data":{}}
