{"id":"xals7sokvxd069dv8jxerq6","title":"ErgoAI","desc":"object-oriented platform for knowledge representation and reasoning","updated":1695851032508,"created":1683049532557,"custom":{},"fname":"prdct.ergoai","type":"note","vault":{"fsPath":"public-notes","remote":{"type":"git","url":"git@github.com:djradon/public-notes.git"},"name":"public-notes"},"contentHash":"669a4830fa3c387ca60fcfc612b9d516","links":[{"type":"wiki","from":{"fname":"prdct.ergoai","id":"xals7sokvxd069dv8jxerq6","vaultName":"public-notes"},"value":"t.cs.languages.abl","position":{"start":{"line":3,"column":15,"offset":60},"end":{"line":3,"column":37,"offset":82},"indent":[]},"xvault":false,"sameFile":false,"to":{"fname":"t.cs.languages.abl"}},{"from":{"fname":"t.km.knowledge-graph.dynamic","id":"xaxbsxbgl6pjx6rdwkek100","vaultName":"public-notes"},"type":"backlink","position":{"start":{"line":4,"column":3,"offset":23},"end":{"line":4,"column":19,"offset":39},"indent":[]},"value":"prdct.ergoai"}],"anchors":{},"children":["8bsycwnw9louhpwzit2lshs","1gikqeseez6fbntilyh5v3w"],"parent":"6q10hkz3zuvnueqa9slqqmu","data":{}}
