{"id":"xq9vgxesuh5by6syanmaw1k","title":"Genesys","desc":"","updated":1727677752978,"created":1727677657027,"custom":{},"fname":"game-system.genesys","type":"note","vault":{"fsPath":"public-notes","remote":{"type":"git","url":"git@github.com:djradon/public-notes.git"},"name":"public-notes"},"contentHash":"9bce3e7ad3b62d909d16c38b5f127f2a","links":[{"type":"ref","from":{"fname":"game-system.genesys","id":"xq9vgxesuh5by6syanmaw1k","vaultName":"public-notes"},"value":"ar.theangrygm.a-complete-idiots-guide-to-play-by-post-gaming","position":{"start":{"line":4,"column":1,"offset":17},"end":{"line":4,"column":80,"offset":96},"indent":[]},"xvault":false,"to":{"fname":"ar.theangrygm.a-complete-idiots-guide-to-play-by-post-gaming","anchorHeader":"^sfwe0h0ipn9l"}},{"type":"ref","from":{"fname":"game-system.genesys","id":"xq9vgxesuh5by6syanmaw1k","vaultName":"public-notes"},"value":"ar.theangrygm.a-complete-idiots-guide-to-play-by-post-gaming","position":{"start":{"line":5,"column":1,"offset":97},"end":{"line":5,"column":80,"offset":176},"indent":[]},"xvault":false,"to":{"fname":"ar.theangrygm.a-complete-idiots-guide-to-play-by-post-gaming","anchorHeader":"^2oeuqdes6i0x"}}],"anchors":{"description":{"type":"header","text":"Description","value":"description","line":8,"column":0,"depth":2}},"children":[],"parent":"vffazi1zsvyoq0axm0c8iej","data":{}}
