{"id":"xqj8k5pm66v75c1ama5g7mi","title":"Matthew Kieran","desc":"","updated":1725994035181,"created":1725994035181,"custom":{},"fname":"user.matthew-kieran","type":"note","vault":{"fsPath":"public-notes","remote":{"type":"git","url":"git@github.com:djradon/public-notes.git"},"name":"public-notes"},"contentHash":"14c82972d5c218d9e830efd3b662fcc2","links":[{"from":{"fname":"ar.creativity-as-an-epistemic-virtue","id":"azvk9tchc6hlwwstrsf7id3","vaultName":"public-notes"},"type":"backlink","position":{"start":{"line":3,"column":11,"offset":100},"end":{"line":3,"column":26,"offset":115},"indent":[]},"value":"user.matthew-kieran"}],"anchors":{},"children":[],"parent":"g24de3ikvaqmy6bp4m223t0","data":{}}
