{"id":"xx8san1pymdwbciw9xijvh0","title":"Design Principles behind Smalltalk","desc":"","updated":1695852238439,"created":1695852167162,"custom":{},"fname":"ar.design-principles-behind-smalltalk","type":"note","vault":{"fsPath":"public-notes","remote":{"type":"git","url":"git@github.com:djradon/public-notes.git"},"name":"public-notes"},"contentHash":"7172ec9a344ee532e3ed73b3f99f0a19","links":[{"type":"wiki","from":{"fname":"ar.design-principles-behind-smalltalk","id":"xx8san1pymdwbciw9xijvh0","vaultName":"public-notes"},"value":"user.daniel-ingalls","alias":"@daniel-ingalls","position":{"start":{"line":3,"column":11,"offset":83},"end":{"line":3,"column":26,"offset":98},"indent":[]},"xvault":false,"to":{"fname":"user.daniel-ingalls"}},{"from":{"fname":"t.cs.languages.smalltalk","id":"rxt1jdkdr6h0mehpqqcr9nv","vaultName":"public-notes"},"type":"backlink","position":{"start":{"line":4,"column":3,"offset":17},"end":{"line":4,"column":44,"offset":58},"indent":[]},"value":"ar.design-principles-behind-smalltalk"}],"anchors":{"summary":{"type":"header","text":"Summary","value":"summary","line":12,"column":0,"depth":2}},"children":[],"parent":"7272514wvvn78ppl0gxbz1o","data":{}}
