{"fname":"pub.question-log.2024.08","stub":true,"vault":{"fsPath":"public-notes","remote":{"type":"git","url":"git@github.com:djradon/public-notes.git"},"name":"public-notes"},"schemaStub":false,"type":"note","updated":1727464086510,"created":1727464086510,"id":"zne8qfwvv0nj3a8o23x1no8","desc":"","links":[],"anchors":{},"children":["tuzqkzulj26kxnn3seeg0ay","29yklmqdve7vg8up1rtknag","rntox133e8g63tuw16jrfz0","3e1tyaecsqu3uptltwo0b74","b6qykrogg32uhr7g5iiv8uq","vj0fma3scceqp9ckbheg9r2","y2w1qox49p7rc1cp99lsmsm"],"parent":"8l8m32qsszzyid10grtde9t","data":{},"title":"08"}
